Workbook

Sheet Actif
A1: Actif | B1: N | C1: N-1 | D1: N-2
A2: Actif non courant
A3: Immobilisations incorporelles | B3: =B4+B5+B6+B7 -> 1107 | C3: =C4+C5+C6+C7 -> 775 | D3: =D4+D5+D6+D7 -> 681
A4: - Goodwill | B4: 635 | C4: 343 | D4: 325
A5: - Marques et droits d'auteur | B5: =Actif!B27 -> 449 | C5: =Actif!C27 -> 409 | D5: =Actif!D27 -> 333
A6: - Brevets et licences | B6: 23 | C6: 23 | D6: 23
A7: - Autres immobilisations incorporelles | B7: 0 | C7: 0 | D7: 0
A8: Immobilisations corporelles | B8: =B9+B10+B11 -> 2126 | C8: =C9+C10+C11 -> 2314 | D8: =D9+D10+D11 -> 2266
A9: - Terrains | B9: 658 | C9: 634 | D9: 546
A10: - Bâtiments | B10: 1456 | C10: 1665 | D10: 1700
A11: - Matériel et équipement | B11: 12 | C11: 15 | D11: 20
A12: Immobilisations financières | B12: =SUM(B13:B14) -> 243 | C12: =SUM(C13:C14) -> 175 | D12: =SUM(D13:D14) -> 44
A13: - Participations dans des sociétés | B13: 243 | C13: 175 | D13: 44
A14: - Prêts à long terme | B14: 0 | C14: 0 | D14: 0
A15: Total Actif non courant | B15: =B3+B8+B12 -> 3476 | C15: =C3+C8+C12 -> 3264 | D15: =D3+D8+D12 -> 2991
A16: Actif courant
A17: Stocks | B17: =SUM(B18:B19) -> 66 | C17: =SUM(C18:C19) -> 91 | D17: =SUM(D18:D19) -> 43
A18: - Matières premières | B18: 22 | C18: 24 | D18: 18
A19: - Produits finis | B19: 44 | C19: 67 | D19: 25
A20: Créances clients | B20: =B21 -> 334 | C20: =C21 -> 278 | D20: =D21 -> 255
A21: - Créances à court terme | B21: 334 | C21: 278 | D21: 255
A22: Autres créances | B22: =B23+B24 -> 15 | C22: =C23+C24 -> 10 | D22: =D23+D24 -> 15
A23: - Avances et acomptes | B23: 0 | C23: 0 | D23: 0
A24: - Créances diverses | B24: 15 | C24: 10 | D24: 15
A25: Trésorerie et équivalents de trésorerie | B25: =B26 -> 34 | C25: =C26 -> 30 | D25: =D26 -> 20
A26: - Disponibilités bancaires | B26: 34 | C26: 30 | D26: 20 | J26: =B28-Passif!B31 -> 0 | K26: =C28-Passif!C31 -> 0 | L26: =D28-Passif!D31 -> 0
A27: Total Actif courant | B27: =B17+B20+B22+B25 -> 449 | C27: =C17+C20+C22+C25 -> 409 | D27: =D17+D20+D22+D25 -> 333
A28: Total Actif | B28: =B15+B27 -> 3925 | C28: =C15+C27 -> 3673 | D28: =D15+D27 -> 3324

Sheet Passif
A1: Passif | B1: N | C1: N-1 | D1: N-2
A2: Capitaux propres
A3: Capital social | B3: 1100 | C3: 1100 | D3: 1100
A4: Primes d'émission | B4: 0 | C4: 0 | D4: 0
A5: Réserves légales | B5: 245 | C5: 245 | D5: 245
A6: Réserves statutaires | B6: 0 | C6: 0 | D6: 0
A7: Réserves facultatives | B7: 0 | C7: 0 | D7: 0
A8: Autres réserves | B8: 12 | C8: 12 | D8: 15
A9: Résultat net reporté | B9: ='Compte de resultat'!B30 -> 183 | C9: ='Compte de resultat'!C30 -> 57 | D9: ='Compte de resultat'!D30 -> 105
A10: Total Capitaux propres | B10: =B3+B4+B5+B6+B7+B8+B9 -> 1540 | C10: =C3+C4+C5+C6+C7+C8+C9 -> 1414 | D10: =D3+D4+D5+D6+D7+D8+D9 -> 1465
A11: Passif non courant
A12: Emprunts et dettes financières à long terme | B12: =B13+B14 -> 1450 | C12: =C13+C14 -> 1350 | D12: =D13+D14 -> 1300
A13: - Emprunts bancaires | B13: 1450 | C13: 1350 | D13: 1300
A14: - Obligations | B14: 0 | C14: 0 | D14: 0
A15: Provisions pour risques et charges | B15: =B16+B17 -> 0 | C15: =C16+C17 -> 0 | D15: =D16+D17 -> 0
A16: - Provisions pour retraites et pensions | B16: 0 | C16: 0 | D16: 0
A17: - Autres provisions | B17: 0 | C17: 0 | D17: 0
A18: Total Passif non courant | B18: =B12+B15 -> 1450 | C18: =C12+C15 -> 1350 | D18: =D12+D15 -> 1300
A19: Passif courant
A20: Fournisseurs et dettes fournisseurs | B20: =B21 -> 11 | C20: =C21 -> 8 | D20: =D21 -> 5
A21: - Dettes à court terme | B21: 11 | C21: 8 | D21: 5
A22: Dettes fiscales et sociales | B22: =B23+B24 -> 38 | C22: =C23+C24 -> 18 | D22: =D23+D24 -> 45
A23: - Impôts sur le revenu | B23: 23 | C23: 13 | D23: 10
A24: - Cotisations sociales | B24: 15 | C24: 5 | D24: 35
A25: Emprunts et dettes financières à court terme | B25: =B26 -> 875 | C25: =C26 -> 763 | D25: =D26 -> 404
A26: - Emprunts bancaires | B26: 875 | C26: 763 | D26: 404
A27: Autres dettes | B27: =B28+B29 -> 11 | C27: =C28+C29 -> 120 | D27: =D28+D29 -> 105
A28: - Dettes diverses | B28: 11 | C28: 120 | D28: 105
A29: - Dividendes à payer | B29: 0 | C29: 0 | D29: 0
A30: Total Passif courant | B30: =B20+B22+B25+B27 -> 935 | C30: =C20+C22+C25+C27 -> 909 | D30: =D20+D22+D25+D27 -> 559
A31: Total Passif | B31: =B10+B18+B30 -> 3925 | C31: =C10+C18+C30 -> 3673 | D31: =D10+D18+D30 -> 3324

Sheet Compte de resultat
A1: Compte de Résultat | B1: N | C1: N-1 | D1: N-2
A2: Produits
A3: Chiffre d'affaires | B3: =B4+B5 -> 2345 | C3: =C4+C5 -> 2004 | D3: =D4+D5 -> 1970
A4: - Ventes de biens | B4: 2345 | C4: 2004 | D4: 1970
A5: - Ventes de services | B5: 0 | C5: 0 | D5: 0
A6: Autres produits opérationnels | B6: =B7+B8 -> 2345 | C6: =C7+C8 -> 1854 | D6: =D7+D8 -> 2005
A7: - Subventions d'exploitation | B7: 2345 | C7: 1854 | D7: 2005
A8: - Revenus exceptionnels | B8: 0 | C8: 0 | D8: 0
A9: Total Produits | B9: =B3+B7+B8 -> 4690 | C9: =C3+C7+C8 -> 3858 | D9: =D3+D7+D8 -> 3975
A10: Charges
A11: Coût des ventes | B11: =B12+B13 -> 1750 | C11: =C12+C13 -> 1570 | D11: =D12+D13 -> 1500
A12: - Achats de matières premières | B12: 1750 | C12: 1570 | D12: 1500
A13: - Autres coûts directs | B13: 0 | C13: 0 | D13: 0
A14: Charges opérationnelles | B14: =B15+B16+B17 -> 2490 | C14: =C15+C16+C17 -> 1954 | D14: =D15+D16+D17 -> 2080
A15: - Salaires et charges sociales | B15: 754 | C15: 740 | D15: 735
A16: - Loyer et charges locatives | B16: 980 | C16: 980 | D16: 980
A17: - Autres charges d'exploitation | B17: 756 | C17: 234 | D17: 365
A18: Amortissements et provisions | B18: =B19+B20 -> 0 | C18: =C19+C20 -> 0 | D18: =D19+D20 -> 0
A19: - Amortissement des immobilisations | B19: 0 | C19: 0 | D19: 0
A20: - Provisions pour risques et charges | B20: 0 | C20: 0 | D20: 0
A21: Total Charges | B21: =B11+B14+B18 -> 4240 | C21: =C11+C14+C18 -> 3524 | D21: =D11+D14+D18 -> 3580
A22: Résultat opérationnel | B22: =B9-B21 -> 450 | C22: =C9-C21 -> 334 | D22: =D9-D21 -> 395
A23: Produits financiers | B23: =B24 -> 0 | C23: =C24 -> 0 | D23: =D24 -> 0
A24: - Revenus financiers | B24: 0 | C24: 0 | D24: 0
A25: Charges financières | B25: =B26 -> 145 | C25: =C26 -> 235 | D25: =D26 -> 167
A26: - Charges d'intérêts | B26: 145 | C26: 235 | D26: 167
A27: Résultat financier | B27: =B23-B25 -> -145 | C27: =C23-C25 -> -235 | D27: =D23-D25 -> -167
A28: Résultat avant impôt | B28: =B22+B27 -> 305 | C28: =C22+C27 -> 99 | D28: =D22+D27 -> 228
A29: Impôt sur les sociétés | B29: 122 | C29: 42 | D29: 123
A30: Résultat net | B30: =B28-B29 -> 183 | C30: =C28-C29 -> 57 | D30: =D28-D29 -> 105

Sheet Ratios
A1: RATIO FINANCIER | B1: N | C1: N-1 | D1: N-2
A2: Rentabilité économique (Return on Assets - ROA) | B2: =('Compte de resultat'!B30/Actif!B28)*100 -> 4.6624204 | C2: =('Compte de resultat'!C30/Actif!C28)*100 -> 1.551865 | D2: =('Compte de resultat'!D30/Actif!D28)*100 -> 3.1588448
A3: Rentabilité des capitaux propres (Return on Equity - ROE) | B3: =('Compte de resultat'!B30/Passif!B10)*100 -> 11.883117 | C3: =('Compte de resultat'!C30/Passif!C10)*100 -> 4.0311174 | D3: =('Compte de resultat'!D30/Passif!D10)*100 -> 7.1672355
A4: LIQUIDITE | B4: N | C4: N-1 | D4: N-2
A5: Liquidité générale | B5: =Actif!B27/Passif!B30 -> 0.4802139 | C5: =Actif!C27/Passif!C30 -> 0.44994499 | D5: =Actif!D27/Passif!D30 -> 0.59570662
A6: Liquidité immédiate | B6: =(Actif!B27-Actif!B17)/Passif!B30 -> 0.40962567 | C6: =(Actif!C27-Actif!C17)/Passif!C30 -> 0.34983498 | D6: =(Actif!D27-Actif!D17)/Passif!D30 -> 0.51878354
A7: SOLVABILITE | B7: N | C7: N-1 | D7: N-2
A8: Ratio d'endettement total | B8: =Passif!B31/Passif!B10 -> 2.5487013 | C8: =Passif!C31/Passif!C10 -> 2.5975955 | D8: =Passif!D31/Passif!D10 -> 2.268942
A9: Ratio de couverture des intérêts | B9: ='Compte de resultat'!B22/'Compte de resultat'!B26 -> 3.1034483 | C9: ='Compte de resultat'!C22/'Compte de resultat'!C26 -> 1.4212766 | D9: ='Compte de resultat'!D22/'Compte de resultat'!D26 -> 2.3652695
A10: RENTABILITE DES VENTES | B10: N | C10: N-1 | D10: N-2
A11: Marge brute | B11: =(('Compte de resultat'!B3-'Compte de resultat'!B11)/'Compte de resultat'!B3)*100 -> 25.373134 | C11: =(('Compte de resultat'!C3-'Compte de resultat'!C11)/'Compte de resultat'!C3)*100 -> 21.656687 | D11: =(('Compte de resultat'!D3-'Compte de resultat'!D11)/'Compte de resultat'!D3)*100 -> 23.857868
A12: Marge opérationnelle | B12: =('Compte de resultat'!B22/'Compte de resultat'!B3)*100 -> 19.189765 | C12: =('Compte de resultat'!C22/'Compte de resultat'!C3)*100 -> 16.666667 | D12: =('Compte de resultat'!D22/'Compte de resultat'!D3)*100 -> 20.050761
A13: Marge nette | B13: =('Compte de resultat'!B30/'Compte de resultat'!B3)*100 -> 7.803838 | C13: =('Compte de resultat'!C30/'Compte de resultat'!C3)*100 -> 2.8443114 | D13: =('Compte de resultat'!D30/'Compte de resultat'!D3)*100 -> 5.3299492
A14: GESTION | B14: N | C14: N-1 | D14: N-2
A15: Rotation des actifs | B15: ='Compte de resultat'!B3/Actif!B28 -> 0.59745223 | C15: ='Compte de resultat'!C3/Actif!C28 -> 0.54560305 | D15: ='Compte de resultat'!D3/Actif!D28 -> 0.59265945
A16: Délai moyen de recouvrement des créances (DSO) | B16: =(Actif!B20/'Compte de resultat'!B3)*365 -> 51.987207 | C16: =(Actif!C20/'Compte de resultat'!C3)*365 -> 50.633733 | D16: =(Actif!D20/'Compte de resultat'!D3)*365 -> 47.246193 | E16: En jours
A20: GRAPHIQUES
